{
  "dema": [
    {
      "period_length": "18m",
      "min_periods": 11,
      "markdown_buy_pct": 1.1245597357964172,
      "markup_sell_pct": 2.600064592278853,
      "markup_pct": 1.0618758754908808,
      "order_type": "taker",
      "sell_stop_pct": 35,
      "buy_stop_pct": 36,
      "profit_stop_enable_pct": 11,
      "profit_stop_pct": 7,
      "ema_short_period": 1,
      "ema_long_period": 77,
      "signal_period": 12,
      "up_trend_threshold": 2,
      "down_trend_threshold": 11,
      "overbought_rsi_periods": 21,
      "overbought_rsi": 82,
      "noise_level_pct": 5,
      "sim": {
        "params": "module.exports = {\"avg_slippage_pct\":0.045,\"buy_stop_pct\":36,\"down_trend_threshold\":11,\"ema_long_period\":77,\"ema_short_period\":1,\"filename\":\"none\",\"markdown_buy_pct\":1.1245597357964172,\"markup_sell_pct\":2.600064592278853,\"max_sell_loss_pct\":25,\"max_slippage_pct\":5,\"min_periods\":11,\"noise_level_pct\":5,\"order_type\":\"taker\",\"overbought_rsi\":82,\"overbought_rsi_periods\":21,\"period\":\"18m\",\"period_length\":\"18m\",\"profit_stop_enable_pct\":11,\"profit_stop_pct\":7,\"rsi_periods\":21,\"selector\":{\"exchange_id\":\"cexio\",\"product_id\":\"BTC-USD\",\"asset\":\"BTC\",\"currency\":\"USD\",\"normalized\":\"cexio.BTC-USD\"},\"sell_stop_pct\":35,\"show_options\":true,\"signal_period\":12,\"strategy\":\"dema\",\"up_trend_threshold\":2,\"start\":\"201801160100\"}",
        "endBalance": 996.82934099,
        "buyHold": 793.46481714,
        "vsBuyHold": 25.62,
        "wins": 0,
        "losses": 1,
        "errorRate": 100,
        "period_length": "18m",
        "days": 2,
        "min_periods": 11,
        "markdown_buy_pct": 1.1245597357964172,
        "markup_sell_pct": 2.600064592278853,
        "order_type": "taker",
        "roi": -0.317,
        "wlRatio": 0,
        "selector": "cexio.BTC-USD",
        "strategy": "dema",
        "frequency": 0.5,
        "fitness": 0.374594347924309
      }
    },
    {
      "period_length": "18m",
      "min_periods": 11,
      "markdown_buy_pct": 2.050029219510944,
      "markup_sell_pct": 2.600064592278853,
      "markup_pct": 1.0618758754908808,
      "order_type": "taker",
      "sell_stop_pct": 35,
      "buy_stop_pct": 0,
      "profit_stop_enable_pct": 11,
      "profit_stop_pct": 7,
      "ema_short_period": 12,
      "ema_long_period": 30,
      "signal_period": 11,
      "up_trend_threshold": 18,
      "down_trend_threshold": 11,
      "overbought_rsi_periods": 21,
      "overbought_rsi": 82,
      "noise_level_pct": 5,
      "sim": {
        "params": "module.exports = {\"avg_slippage_pct\":0.045,\"buy_stop_pct\":0,\"down_trend_threshold\":11,\"ema_long_period\":30,\"ema_short_period\":12,\"filename\":\"none\",\"markdown_buy_pct\":2.050029219510944,\"markup_sell_pct\":2.600064592278853,\"max_sell_loss_pct\":25,\"max_slippage_pct\":5,\"min_periods\":11,\"noise_level_pct\":5,\"order_type\":\"taker\",\"overbought_rsi\":82,\"overbought_rsi_periods\":21,\"period\":\"18m\",\"period_length\":\"18m\",\"profit_stop_enable_pct\":11,\"profit_stop_pct\":7,\"rsi_periods\":21,\"selector\":{\"exchange_id\":\"cexio\",\"product_id\":\"BTC-USD\",\"asset\":\"BTC\",\"currency\":\"USD\",\"normalized\":\"cexio.BTC-USD\"},\"sell_stop_pct\":35,\"show_options\":true,\"signal_period\":11,\"strategy\":\"dema\",\"up_trend_threshold\":18,\"start\":\"201801160100\"}",
        "endBalance": 1006.15330522,
        "buyHold": 793.46481714,
        "vsBuyHold": 26.8,
        "wins": 1,
        "losses": 0,
        "errorRate": 0,
        "period_length": "18m",
        "days": 2,
        "min_periods": 11,
        "markdown_buy_pct": 2.050029219510944,
        "markup_sell_pct": 2.600064592278853,
        "order_type": "taker",
        "roi": 0.615,
        "wlRatio": "Infinity",
        "selector": "cexio.BTC-USD",
        "strategy": "dema",
        "frequency": 0.5,
        "fitness": 0.3918473272588401
      }
    },
    {
      "period_length": "18m",
      "min_periods": 11,
      "markdown_buy_pct": -0.1391845777933325,
      "markup_sell_pct": 1.3212155251475384,
      "markup_pct": 1.0618758754908808,
      "order_type": "taker",
      "sell_stop_pct": 18,
      "buy_stop_pct": 36,
      "profit_stop_enable_pct": 5,
      "profit_stop_pct": 17,
      "ema_short_period": 1,
      "ema_long_period": 77,
      "signal_period": 15,
      "up_trend_threshold": 11,
      "down_trend_threshold": 47,
      "overbought_rsi_periods": 25,
      "overbought_rsi": 82,
      "noise_level_pct": 5,
      "sim": {
        "params": "module.exports = {\"avg_slippage_pct\":0.045,\"buy_stop_pct\":36,\"down_trend_threshold\":47,\"ema_long_period\":77,\"ema_short_period\":1,\"filename\":\"none\",\"markdown_buy_pct\":-0.1391845777933325,\"markup_sell_pct\":1.3212155251475384,\"max_sell_loss_pct\":25,\"max_slippage_pct\":5,\"min_periods\":11,\"noise_level_pct\":5,\"order_type\":\"taker\",\"overbought_rsi\":82,\"overbought_rsi_periods\":25,\"period\":\"18m\",\"period_length\":\"18m\",\"profit_stop_enable_pct\":5,\"profit_stop_pct\":17,\"rsi_periods\":25,\"selector\":{\"exchange_id\":\"cexio\",\"product_id\":\"BTC-USD\",\"asset\":\"BTC\",\"currency\":\"USD\",\"normalized\":\"cexio.BTC-USD\"},\"sell_stop_pct\":18,\"show_options\":true,\"signal_period\":15,\"strategy\":\"dema\",\"up_trend_threshold\":11,\"start\":\"201801160100\"}",
        "endBalance": 1026.39991032,
        "buyHold": 793.46481714,
        "vsBuyHold": 29.35,
        "wins": 1,
        "losses": 0,
        "errorRate": 0,
        "period_length": "18m",
        "days": 2,
        "min_periods": 11,
        "markdown_buy_pct": -0.1391845777933325,
        "markup_sell_pct": 1.3212155251475384,
        "order_type": "taker",
        "roi": 2.64,
        "wlRatio": "Infinity",
        "selector": "cexio.BTC-USD",
        "strategy": "dema",
        "frequency": 0.5,
        "fitness": 0.42913130802414023
      }
    },
    {
      "period_length": "18m",
      "min_periods": 11,
      "markdown_buy_pct": 1.1245597357964172,
      "markup_sell_pct": 2.600064592278853,
      "markup_pct": 1.0618758754908808,
      "order_type": "maker",
      "sell_stop_pct": 35,
      "buy_stop_pct": 36,
      "profit_stop_enable_pct": 11,
      "profit_stop_pct": 7,
      "ema_short_period": 1,
      "ema_long_period": 38,
      "signal_period": 12,
      "up_trend_threshold": 2,
      "down_trend_threshold": 11,
      "overbought_rsi_periods": 21,
      "overbought_rsi": 82,
      "noise_level_pct": 5,
      "sim": {
        "params": "module.exports = {\"avg_slippage_pct\":0.045,\"buy_stop_pct\":36,\"down_trend_threshold\":11,\"ema_long_period\":38,\"ema_short_period\":1,\"filename\":\"none\",\"markdown_buy_pct\":1.1245597357964172,\"markup_sell_pct\":2.600064592278853,\"max_sell_loss_pct\":25,\"max_slippage_pct\":5,\"min_periods\":11,\"noise_level_pct\":5,\"order_type\":\"maker\",\"overbought_rsi\":82,\"overbought_rsi_periods\":21,\"period\":\"18m\",\"period_length\":\"18m\",\"profit_stop_enable_pct\":11,\"profit_stop_pct\":7,\"rsi_periods\":21,\"selector\":{\"exchange_id\":\"cexio\",\"product_id\":\"BTC-USD\",\"asset\":\"BTC\",\"currency\":\"USD\",\"normalized\":\"cexio.BTC-USD\"},\"sell_stop_pct\":35,\"show_options\":true,\"signal_period\":12,\"strategy\":\"dema\",\"up_trend_threshold\":2,\"start\":\"201801160100\"}",
        "endBalance": 1079.06097225,
        "buyHold": 793.46481714,
        "vsBuyHold": 35.99,
        "wins": 1,
        "losses": 0,
        "errorRate": 0,
        "period_length": "18m",
        "days": 2,
        "min_periods": 11,
        "markdown_buy_pct": 1.1245597357964172,
        "markup_sell_pct": 2.600064592278853,
        "order_type": "maker",
        "roi": 7.906,
        "wlRatio": "Infinity",
        "selector": "cexio.BTC-USD",
        "strategy": "dema",
        "frequency": 0.5,
        "fitness": 0.526215869703196
      }
    },
    {
      "period_length": "22m",
      "min_periods": 10,
      "markdown_buy_pct": 0.20836368027473418,
      "markup_sell_pct": 1.494597038522775,
      "markup_pct": 0.3088985972421465,
      "order_type": "taker",
      "sell_stop_pct": 0,
      "buy_stop_pct": 0,
      "profit_stop_enable_pct": 0,
      "profit_stop_pct": 11,
      "ema_short_period": 2,
      "ema_long_period": 66,
      "signal_period": 9,
      "up_trend_threshold": 40,
      "down_trend_threshold": 40,
      "overbought_rsi_periods": 14,
      "overbought_rsi": 86,
      "noise_level_pct": 4,
      "sim": {
        "params": "module.exports = {\"avg_slippage_pct\":0.045,\"buy_stop_pct\":0,\"down_trend_threshold\":40,\"ema_long_period\":66,\"ema_short_period\":2,\"filename\":\"none\",\"markdown_buy_pct\":0.20836368027473418,\"markup_sell_pct\":1.494597038522775,\"max_sell_loss_pct\":25,\"max_slippage_pct\":5,\"min_periods\":10,\"noise_level_pct\":4,\"order_type\":\"taker\",\"overbought_rsi\":86,\"overbought_rsi_periods\":14,\"period\":\"22m\",\"period_length\":\"22m\",\"profit_stop_enable_pct\":0,\"profit_stop_pct\":11,\"rsi_periods\":14,\"selector\":{\"exchange_id\":\"cexio\",\"product_id\":\"BTC-USD\",\"asset\":\"BTC\",\"currency\":\"USD\",\"normalized\":\"cexio.BTC-USD\"},\"sell_stop_pct\":0,\"show_options\":true,\"signal_period\":9,\"strategy\":\"dema\",\"up_trend_threshold\":40,\"start\":\"201801160100\"}",
        "endBalance": 1010.37895958,
        "buyHold": 793.46481714,
        "vsBuyHold": 27.33,
        "wins": 1,
        "losses": 0,
        "errorRate": 0,
        "period_length": "22m",
        "days": 2,
        "min_periods": 10,
        "markdown_buy_pct": 0.20836368027473418,
        "markup_sell_pct": 1.494597038522775,
        "order_type": "taker",
        "roi": 1.038,
        "wlRatio": "Infinity",
        "selector": "cexio.BTC-USD",
        "strategy": "dema",
        "frequency": 0.5,
        "fitness": 0.3995965467904514
      }
    },
    {
      "period_length": "7m",
      "min_periods": 30,
      "markdown_buy_pct": -0.364323560985476,
      "markup_sell_pct": 4.347276384209707,
      "markup_pct": 2.8890172769879587,
      "order_type": "taker",
      "sell_stop_pct": 0,
      "buy_stop_pct": 35,
      "profit_stop_enable_pct": 18,
      "profit_stop_pct": 14,
      "ema_short_period": 12,
      "ema_long_period": 100,
      "signal_period": 11,
      "up_trend_threshold": 39,
      "down_trend_threshold": 35,
      "overbought_rsi_periods": 27,
      "overbought_rsi": 90,
      "noise_level_pct": 0,
      "sim": {
        "params": "module.exports = {\"avg_slippage_pct\":0.045,\"buy_stop_pct\":35,\"down_trend_threshold\":35,\"ema_long_period\":100,\"ema_short_period\":12,\"filename\":\"none\",\"markdown_buy_pct\":-0.364323560985476,\"markup_sell_pct\":4.347276384209707,\"max_sell_loss_pct\":25,\"max_slippage_pct\":5,\"min_periods\":30,\"noise_level_pct\":0,\"order_type\":\"taker\",\"overbought_rsi\":90,\"overbought_rsi_periods\":27,\"period\":\"7m\",\"period_length\":\"7m\",\"profit_stop_enable_pct\":18,\"profit_stop_pct\":14,\"rsi_periods\":27,\"selector\":{\"exchange_id\":\"cexio\",\"product_id\":\"BTC-USD\",\"asset\":\"BTC\",\"currency\":\"USD\",\"normalized\":\"cexio.BTC-USD\"},\"sell_stop_pct\":0,\"show_options\":true,\"signal_period\":11,\"strategy\":\"dema\",\"up_trend_threshold\":39,\"start\":\"201801160100\"}",
        "endBalance": 1031.27619579,
        "buyHold": 793.46481714,
        "vsBuyHold": 29.97,
        "wins": 1,
        "losses": 0,
        "errorRate": 0,
        "period_length": "7m",
        "days": 2,
        "min_periods": 30,
        "markdown_buy_pct": -0.364323560985476,
        "markup_sell_pct": 4.347276384209707,
        "order_type": "taker",
        "roi": 3.128,
        "wlRatio": "Infinity",
        "selector": "cexio.BTC-USD",
        "strategy": "dema",
        "frequency": 0.5,
        "fitness": 0.4381964327592327
      }
    },
    {
      "period_length": "18m",
      "min_periods": 11,
      "markdown_buy_pct": 1.1245597357964172,
      "markup_sell_pct": 1.140969610615855,
      "markup_pct": 1.0618758754908808,
      "order_type": "taker",
      "sell_stop_pct": 0,
      "buy_stop_pct": 36,
      "profit_stop_enable_pct": 0,
      "profit_stop_pct": 7,
      "ema_short_period": 1,
      "ema_long_period": 77,
      "signal_period": 12,
      "up_trend_threshold": 48,
      "down_trend_threshold": 11,
      "overbought_rsi_periods": 21,
      "overbought_rsi": 82,
      "noise_level_pct": 5,
      "sim": {
        "params": "module.exports = {\"avg_slippage_pct\":0.045,\"buy_stop_pct\":36,\"down_trend_threshold\":11,\"ema_long_period\":77,\"ema_short_period\":1,\"filename\":\"none\",\"markdown_buy_pct\":1.1245597357964172,\"markup_sell_pct\":1.140969610615855,\"max_sell_loss_pct\":25,\"max_slippage_pct\":5,\"min_periods\":11,\"noise_level_pct\":5,\"order_type\":\"taker\",\"overbought_rsi\":82,\"overbought_rsi_periods\":21,\"period\":\"18m\",\"period_length\":\"18m\",\"profit_stop_enable_pct\":0,\"profit_stop_pct\":7,\"rsi_periods\":21,\"selector\":{\"exchange_id\":\"cexio\",\"product_id\":\"BTC-USD\",\"asset\":\"BTC\",\"currency\":\"USD\",\"normalized\":\"cexio.BTC-USD\"},\"sell_stop_pct\":0,\"show_options\":true,\"signal_period\":12,\"strategy\":\"dema\",\"up_trend_threshold\":48,\"start\":\"201801160100\"}",
        "endBalance": 999.85086878,
        "buyHold": 795.89429104,
        "vsBuyHold": 25.62,
        "wins": 1,
        "losses": 0,
        "errorRate": 0,
        "period_length": "18m",
        "days": 2,
        "min_periods": 11,
        "markdown_buy_pct": 1.1245597357964172,
        "markup_sell_pct": 1.140969610615855,
        "order_type": "taker",
        "roi": -0.015,
        "wlRatio": "Infinity",
        "selector": "cexio.BTC-USD",
        "strategy": "dema",
        "frequency": 0.5,
        "fitness": 0.374594347924309
      }
    },
    {
      "period_length": "18m",
      "min_periods": 11,
      "markdown_buy_pct": 1.1245597357964172,
      "markup_sell_pct": 1.140969610615855,
      "markup_pct": 1.0618758754908808,
      "order_type": "taker",
      "sell_stop_pct": 0,
      "buy_stop_pct": 36,
      "profit_stop_enable_pct": 0,
      "profit_stop_pct": 7,
      "ema_short_period": 1,
      "ema_long_period": 77,
      "signal_period": 11,
      "up_trend_threshold": 48,
      "down_trend_threshold": 5,
      "overbought_rsi_periods": 21,
      "overbought_rsi": 75,
      "noise_level_pct": 2,
      "sim": {
        "params": "module.exports = {\"avg_slippage_pct\":0.045,\"buy_stop_pct\":36,\"down_trend_threshold\":5,\"ema_long_period\":77,\"ema_short_period\":1,\"filename\":\"none\",\"markdown_buy_pct\":1.1245597357964172,\"markup_sell_pct\":1.140969610615855,\"max_sell_loss_pct\":25,\"max_slippage_pct\":5,\"min_periods\":11,\"noise_level_pct\":2,\"order_type\":\"taker\",\"overbought_rsi\":75,\"overbought_rsi_periods\":21,\"period\":\"18m\",\"period_length\":\"18m\",\"profit_stop_enable_pct\":0,\"profit_stop_pct\":7,\"rsi_periods\":21,\"selector\":{\"exchange_id\":\"cexio\",\"product_id\":\"BTC-USD\",\"asset\":\"BTC\",\"currency\":\"USD\",\"normalized\":\"cexio.BTC-USD\"},\"sell_stop_pct\":0,\"show_options\":true,\"signal_period\":11,\"strategy\":\"dema\",\"up_trend_threshold\":48,\"start\":\"201801160100\"}",
        "endBalance": 999.85086878,
        "buyHold": 795.89429104,
        "vsBuyHold": 25.62,
        "wins": 1,
        "losses": 0,
        "errorRate": 0,
        "period_length": "18m",
        "days": 2,
        "min_periods": 11,
        "markdown_buy_pct": 1.1245597357964172,
        "markup_sell_pct": 1.140969610615855,
        "order_type": "taker",
        "roi": -0.015,
        "wlRatio": "Infinity",
        "selector": "cexio.BTC-USD",
        "strategy": "dema",
        "frequency": 0.5,
        "fitness": 0.374594347924309
      }
    }
  ]
}